<widget>
  <widgetClass>tooltwist.wbd.FrameWidget</widgetClass>
  <idWithinRootWidget></idWithinRootWidget>
  <description>List Price Popup Frame</description>
  <rows>1</rows>
  <currentCell>NW</currentCell>
  <suffix>png</suffix>
  <cropX>0</cropX>
  <cropY>0</cropY>
  <cropWidth>8</cropWidth>
  <cropHeight>12</cropHeight>
  <coordinates>F0,0,15,30/16,0,123,30/138,0,14,30:V0,31,15,15/16,31,123,15/138,31,14,15:F0,94,15,15/16,94,123,15/138,94,14,15</coordinates>
  <cell>
    <index>row1</index>
  </cell>
</widget>
